MANIFEST.in
README.md
setup.py
WoeUSB/__init__.py
WoeUSB/core.py
WoeUSB/gui.py
WoeUSB/list_devices.py
WoeUSB/miscellaneous.py
WoeUSB/utils.py
WoeUSB/woeusb
WoeUSB/woeusbgui
WoeUSB/workaround.py
WoeUSB/data/c501-logo.png
WoeUSB/data/icon.ico
WoeUSB/data/woeusb-logo.png
WoeUSB/locale/woeusb.pot
WoeUSB/locale/de/LC_MESSAGES/woeusb.mo
WoeUSB/locale/de/LC_MESSAGES/woeusb.po
WoeUSB/locale/fr/LC_MESSAGES/woeusb.mo
WoeUSB/locale/fr/LC_MESSAGES/woeusb.po
WoeUSB/locale/pl/LC_MESSAGES/woeusb.mo
WoeUSB/locale/pl/LC_MESSAGES/woeusb.po
WoeUSB/locale/pt_BR/LC_MESSAGES/woeusb.mo
WoeUSB/locale/pt_BR/LC_MESSAGES/woeusb.po
WoeUSB/locale/sv/LC_MESSAGES/woeusb.mo
WoeUSB/locale/sv/LC_MESSAGES/woeusb.po
WoeUSB/locale/tr/LC_MESSAGES/woeusb.mo
WoeUSB/locale/tr/LC_MESSAGES/woeusb.po
WoeUSB/locale/zh/LC_MESSAGES/woeusb.mo
WoeUSB/locale/zh/LC_MESSAGES/woeusb.po
WoeUSB_ng.egg-info/PKG-INFO
WoeUSB_ng.egg-info/SOURCES.txt
WoeUSB_ng.egg-info/dependency_links.txt
WoeUSB_ng.egg-info/not-zip-safe
WoeUSB_ng.egg-info/requires.txt
WoeUSB_ng.egg-info/top_level.txt
miscellaneous/WoeUSB-ng.desktop
miscellaneous/com.github.woeusb.woeusb-ng.policy