Metadata-Version: 2.1
Name: WoeUSB-ng
Version: 0.2.12
Summary: WoeUSB-ng is a simple tool that enable you to create your own usb stick windows installer from an iso image or a real DVD. This is a rewrite of original WoeUSB. 
Home-page: https://github.com/WoeUSB/WoeUSB-ng
Author: Jakub Szymański
Author-email: jakubmateusz@poczta.onet.pl
License: GPL-3
